bromelia/__init__.py
bromelia/__version__.py
bromelia/_internal_utils.py
bromelia/avps.py
bromelia/base.py
bromelia/bromelia.py
bromelia/config.py
bromelia/constants.py
bromelia/definitions.py
bromelia/exceptions.py
bromelia/messages.py
bromelia/process.py
bromelia/proxy.py
bromelia/setup.py
bromelia/statemachine.py
bromelia/transport.py
bromelia/types.py
bromelia/utils.py
bromelia/avps/__init__.py
bromelia/avps/etsi_3gpp/__init__.py
bromelia/avps/etsi_3gpp/ts_129_061.py
bromelia/avps/etsi_3gpp/ts_129_212.py
bromelia/avps/etsi_3gpp/ts_129_214.py
bromelia/avps/etsi_3gpp/ts_129_229.py
bromelia/avps/etsi_3gpp/ts_129_272.py
bromelia/avps/etsi_3gpp/ts_129_273.py
bromelia/avps/etsi_3gpp/ts_129_329.py
bromelia/avps/etsi_3gpp/ts_183_017.py
bromelia/avps/ietf/__init__.py
bromelia/avps/ietf/rfc4006.py
bromelia/avps/ietf/rfc4072.py
bromelia/avps/ietf/rfc5447.py
bromelia/avps/ietf/rfc6733.py
bromelia/avps/ietf/rfc7155.py
bromelia/avps/ietf/rfc8506.py
bromelia/constants/__init__.py
bromelia/constants/app_ids.py
bromelia/constants/experimental_result_codes.py
bromelia/constants/flags.py
bromelia/constants/general.py
bromelia/constants/result_codes.py
bromelia/constants/etsi_3gpp/__init__.py
bromelia/constants/etsi_3gpp/ts_129_061.py
bromelia/constants/etsi_3gpp/ts_129_212.py
bromelia/constants/etsi_3gpp/ts_129_214.py
bromelia/constants/etsi_3gpp/ts_129_229.py
bromelia/constants/etsi_3gpp/ts_129_272.py
bromelia/constants/etsi_3gpp/ts_129_273.py
bromelia/constants/etsi_3gpp/ts_129_329.py
bromelia/constants/etsi_3gpp/ts_183_017.py
bromelia/constants/ietf/__init__.py
bromelia/constants/ietf/rfc4006.py
bromelia/constants/ietf/rfc4072.py
bromelia/constants/ietf/rfc5447.py
bromelia/constants/ietf/rfc6733.py
bromelia/constants/ietf/rfc7155.py
bromelia/constants/ietf/rfc8506.py
bromelia/etsi_3gpp_gx/__init__.py
bromelia/etsi_3gpp_gx/avps.py
bromelia/etsi_3gpp_gx/messages.py
bromelia/etsi_3gpp_rx/__init__.py
bromelia/etsi_3gpp_rx/avps.py
bromelia/etsi_3gpp_rx/messages.py
bromelia-0.3.1.dist-info/LICENSE.md
bromelia-0.3.1.dist-info/METADATA
bromelia-0.3.1.dist-info/WHEEL
bromelia-0.3.1.dist-info/top_level.txt
bromelia-0.3.1.dist-info/RECORD
