Metadata-Version: 2.1
Name: bromelia
Version: 0.3.1
Summary: A Python micro framework for Diameter applications
Home-page: https://github.com/heimiricmr/bromelia
Author: Henrique Marques Ribeiro
Author-email: heimiricmr@gmail.com
License: MIT
Download-URL: https://github.com/heimiricmr/bromelia/releases/tag/v0.3.1
Keywords: DIAMETER,3GPP,EPC,4G,IMS,TELECOM,TELCO,RFC6733,RFC3588,IETF,VoLTE,VoWiFi
Platform: UNKNOWN
Classifier: Development Status :: 3 - Alpha
Classifier: Intended Audience :: Developers
Classifier: Intended Audience :: Telecommunications Industry
Classifier: License :: OSI Approved :: MIT License
Classifier: Operating System :: OS Independent
Classifier: Programming Language :: Python :: 3 :: Only
Classifier: Programming Language :: Python :: 3
Classifier: Programming Language :: Python :: 3.7
Classifier: Programming Language :: Python :: 3.8
Classifier: Programming Language :: Python :: 3.9
Classifier: Programming Language :: Python :: Implementation :: CPython
Classifier: Topic :: Software Development :: Libraries :: Python Modules
Classifier: Topic :: Communications :: Telephony
Requires-Python: >=3.7
License-File: LICENSE.md
Requires-Dist: pyyaml
